kiwify_userAPI/__init__.py
kiwify_userAPI/__version__.py
kiwify_userAPI/api.py
kiwify_userAPI/authenticate.py
kiwify_userAPI/bultins.py
kiwify_userAPI/exeptions.py
kiwify_userAPI/kiwify.py
kiwify_userAPI/sections.py
kiwify_userAPI/.cache/.kiwify_userAPI
kiwify_userAPI/.cache/.refresh
kiwify_userAPI-1.0.0.0.dist-info/LICENSE
kiwify_userAPI-1.0.0.0.dist-info/METADATA
kiwify_userAPI-1.0.0.0.dist-info/WHEEL
kiwify_userAPI-1.0.0.0.dist-info/top_level.txt
kiwify_userAPI-1.0.0.0.dist-info/RECORD
