Metadata-Version: 2.2
Name: kiwify_userAPI
Version: 1.0.0.0
Summary: Obtenha detalhes de cursos que o usuário esteja inscrito da plataforma kiwify,usando o EndPoint 
Author: PauloCesar-dev404
Author-email: paulocesar0073dev404@gmail.com
License: MIT
Project-URL: GitHub, https://github.com/PauloCesar-dev404/kiwify-userAPI
Keywords: kiwify python,kiwify,kiwify_userAPI,kiwify api,kiwify-userAPI
Platform: any
License-File: LICENSE
Requires-Dist: requests
Requires-Dist: cloudscraper
Dynamic: author
Dynamic: author-email
Dynamic: description
Dynamic: description-content-type
Dynamic: keywords
Dynamic: license
Dynamic: platform
Dynamic: project-url
Dynamic: requires-dist
Dynamic: summary
